janus_sdk/__init__.py
janus_sdk/multimodal.py
janus_sdk/webhook_trigger.py
janus_python_sdk-0.3.0.dist-info/METADATA
janus_python_sdk-0.3.0.dist-info/WHEEL
janus_python_sdk-0.3.0.dist-info/licenses/LICENSE
janus_python_sdk-0.3.0.dist-info/RECORD
