Metadata-Version: 2.4
Name: janus-python-sdk
Version: 0.3.0
Summary: Automatically stress-test your AI apps. Sign up for an api key at withjanus.com
Project-URL: Homepage, https://withjanus.com
Project-URL: Repository, https://github.com/Janus-AI-Inc/janus-python-sdk
Project-URL: Issues, https://github.com/Janus-AI-Inc/janus-python-sdk/issues
Author-email: Janus AI <team@withjanus.com>
License: MIT License
License-File: LICENSE
Keywords: ai,api,async,http,janus,sdk
Classifier: Operating System :: OS Independent
Classifier: Programming Language :: Python
Classifier: Programming Language :: Python :: 3
Classifier: Programming Language :: Python :: 3 :: Only
Classifier: Programming Language :: Python :: 3.9
Requires-Python: >=3.9
Requires-Dist: httpx<1.0,>=0.23
Requires-Dist: openai>=1.0
Requires-Dist: opentelemetry-api>=1.20.0
Requires-Dist: opentelemetry-exporter-otlp-proto-http>=1.20.0
Requires-Dist: opentelemetry-sdk>=1.20.0
Requires-Dist: python-dotenv>=1.0
Requires-Dist: rich<14.0,>=13.0
Requires-Dist: tiktoken>=0.5.1
Provides-Extra: examples
